home_hunt_error_handler-0.1.0.dist-info/licenses/LICENSE
home_hunt_error_pkg/__init__.py
home_hunt_error_pkg/aws_errors.py
home_hunt_error_pkg/dynamo_errors.py
home_hunt_error_pkg/exceptions.py
home_hunt_error_pkg/validators.py
home_hunt_error_handler-0.1.0.dist-info/METADATA
home_hunt_error_handler-0.1.0.dist-info/WHEEL
home_hunt_error_handler-0.1.0.dist-info/top_level.txt
home_hunt_error_handler-0.1.0.dist-info/RECORD
