Metadata-Version: 2.4
Name: home_hunt_error_handler
Version: 0.1.0
Summary: A custom library for handling errors in real estate application Home Hunt.
Home-page: https://github.com/nikhildhoke/home_hunt_error_handler
Author: Nikhil Dhoke
Author-email: nikhildhoke1995@example.com
License: MIT
Classifier: Operating System :: OS Independent
Classifier: Programming Language :: Python :: 3
Requires-Python: >=3.6
License-File: LICENSE
Requires-Dist: boto3
Provides-Extra: dev
Requires-Dist: check-manifest; extra == "dev"
Provides-Extra: test
Requires-Dist: coverage; extra == "test"
Dynamic: author
Dynamic: author-email
Dynamic: classifier
Dynamic: description
Dynamic: description-content-type
Dynamic: home-page
Dynamic: license
Dynamic: license-file
Dynamic: provides-extra
Dynamic: requires-dist
Dynamic: requires-python
Dynamic: summary
